safa_cmd/__init__.py
safa_cmd/config.py
safa_cmd/constants.py
safa_cmd/runner.py
safa_cmd/data/__init__.py
safa_cmd/data/artifact_json.py
safa_cmd/data/file_change.py
safa_cmd/tools/__init__.py
safa_cmd/tools/comitter/__init__.py
safa_cmd/tools/comitter/generate.py
safa_cmd/tools/comitter/git_helpers.py
safa_cmd/tools/comitter/runner.py
safa_cmd/tools/configure/__init__.py
safa_cmd/tools/configure/runner.py
safa_cmd/tools/safa/__init__.py
safa_cmd/tools/safa/projects.py
safa_cmd/utils/__init__.py
safa_cmd/utils/fs.py
safa_cmd/utils/llm_manager.py
safa_cmd/utils/markdown.py
safa_cmd/utils/menu.py
safa_cmd/utils/printers.py
safa_cmd-0.0.9.dist-info/METADATA
safa_cmd-0.0.9.dist-info/WHEEL
safa_cmd-0.0.9.dist-info/entry_points.txt
safa_cmd-0.0.9.dist-info/top_level.txt
safa_cmd-0.0.9.dist-info/RECORD
