Metadata-Version: 2.1
Name: safa-cmd
Version: 0.0.9
Summary: A command line tool for running SAFA in the command line.
Author-email: Alberto Rodriguez <alberto@safa.ai.com>
License: MIT
Project-URL: Homepage, https://github.com/thearod5/commit-fixer
Requires-Python: >=3.10
Requires-Dist: aiohttp ==3.9.5
Requires-Dist: aiosignal ==1.3.1
Requires-Dist: annotated-types ==0.7.0
Requires-Dist: anthropic ==0.30.0
Requires-Dist: anyio ==4.4.0
Requires-Dist: async-timeout ==4.0.3
Requires-Dist: attrs ==23.2.0
Requires-Dist: certifi ==2024.6.2
Requires-Dist: charset-normalizer ==3.3.2
Requires-Dist: dataclasses-json ==0.6.7
Requires-Dist: defusedxml ==0.7.1
Requires-Dist: distro ==1.9.0
Requires-Dist: exceptiongroup ==1.2.1
Requires-Dist: filelock ==3.15.4
Requires-Dist: frozenlist ==1.4.1
Requires-Dist: fsspec ==2024.6.1
Requires-Dist: gitdb ==4.0.11
Requires-Dist: GitPython ==3.1.43
Requires-Dist: greenlet ==3.0.3
Requires-Dist: h11 ==0.14.0
Requires-Dist: httpcore ==1.0.5
Requires-Dist: httpx ==0.27.0
Requires-Dist: huggingface-hub ==0.23.4
Requires-Dist: idna ==3.7
Requires-Dist: jiter ==0.5.0
Requires-Dist: jsonpatch ==1.33
Requires-Dist: jsonpointer ==3.0.0
Requires-Dist: langchain ==0.2.6
Requires-Dist: langchain-anthropic ==0.1.17
Requires-Dist: langchain-community ==0.2.6
Requires-Dist: langchain-core ==0.2.10
Requires-Dist: langchain-text-splitters ==0.2.2
Requires-Dist: langsmith ==0.1.82
Requires-Dist: marshmallow ==3.21.3
Requires-Dist: multidict ==6.0.5
Requires-Dist: mypy-extensions ==1.0.0
Requires-Dist: numpy ==1.26.4
Requires-Dist: openai ==1.35.7
Requires-Dist: orjson ==3.10.5
Requires-Dist: packaging ==24.1
Requires-Dist: pydantic ==2.7.4
Requires-Dist: pydantic-core ==2.18.4
Requires-Dist: python-dotenv ==1.0.1
Requires-Dist: PyYAML ==6.0.1
Requires-Dist: requests ==2.32.3
Requires-Dist: safa-sdk
Requires-Dist: smmap ==5.0.1
Requires-Dist: sniffio ==1.3.1
Requires-Dist: SQLAlchemy ==2.0.31
Requires-Dist: tenacity ==8.4.2
Requires-Dist: tokenizers ==0.19.1
Requires-Dist: tqdm ==4.66.4
Requires-Dist: typing-inspect ==0.9.0
Requires-Dist: typing-extensions ==4.12.2
Requires-Dist: urllib3 ==2.2.2
Requires-Dist: yarl ==1.9.4
